ruft/__init__.py
ruft/module1.py
ruft_lib-0.4.dist-info/licenses/AUTHORS.md
ruft_lib-0.4.dist-info/licenses/LICENSE
ruft_lib-0.4.dist-info/METADATA
ruft_lib-0.4.dist-info/WHEEL
ruft_lib-0.4.dist-info/top_level.txt
ruft_lib-0.4.dist-info/RECORD
