Metadata-Version: 2.4
Name: ruft-lib
Version: 0.4
Summary: This is a prototype package for generating rules from raw text
Author: Olegs Verhodubs
Author-email: oleg.verhodub@inbox.lv
License: Apache-2.0
Keywords: rules,text,natural language processing,python
Classifier: Programming Language :: Python :: 3.13
Classifier: License :: OSI Approved :: Apache Software License
Classifier: Operating System :: OS Independent
Requires-Python: >=3.13
License-File: LICENSE
License-File: AUTHORS.md
Requires-Dist: nltk>=3.9.2
Dynamic: author
Dynamic: author-email
Dynamic: classifier
Dynamic: description
Dynamic: description-content-type
Dynamic: keywords
Dynamic: license
Dynamic: license-file
Dynamic: requires-dist
Dynamic: requires-python
Dynamic: summary
